robotframework_restbridge/RestBridge.py
robotframework_restbridge/__init__.py
robotframework_restbridge-0.1.0.dist-info/METADATA
robotframework_restbridge-0.1.0.dist-info/WHEEL
robotframework_restbridge-0.1.0.dist-info/top_level.txt
robotframework_restbridge-0.1.0.dist-info/RECORD
