Metadata-Version: 2.1
Name: robotframework-restbridge
Version: 0.1.0
Summary: This is a robotframework keyword library to allow single command execution via HTTP.
Home-page: https://github.com/raffelino/robotframework-restbridge
Author: Your Name
Author-email: PyPI.Releases@viadee.de
Classifier: Intended Audience :: Developers
Classifier: License :: OSI Approved :: Apache Software License
Classifier: Programming Language :: Python :: 3.6
Classifier: Programming Language :: Python :: 3.7
Classifier: Programming Language :: Python :: 3.8
Classifier: Programming Language :: Python :: 3.9
Classifier: Operating System :: OS Independent
Requires-Dist: robotframework
